baro/__init__.py
baro-5.7.2.dist-info/METADATA
baro-5.7.2.dist-info/WHEEL
baro-5.7.2.dist-info/top_level.txt
baro-5.7.2.dist-info/RECORD
